Faloodeh/__init__.py
Faloodeh/conftest.py
Faloodeh/framwork_test.py
Faloodeh/wsgi_test.py
Faloodeh/Faloodeh_Framwork/__init__.py
Faloodeh/Faloodeh_Framwork/middleware.py
Faloodeh/Faloodeh_SqlAlchemy/__init__.py
Faloodeh/Faloodeh_SqlAlchemy/models.py
Faloodeh/Faloodeh_UI/__init__.py
Faloodeh/Faloodeh_UI/base_html_element.py
Faloodeh/Faloodeh_UI/html_elements.py
Faloodeh/Faloodeh_UI/inline_internal_css.py
Faloodeh/Faloodeh_UI/internal_javascript.py
Faloodeh/Faloodeh_UI/test.py
Faloodeh/Faloodeh_WSGI/__init__.py
Faloodeh/Faloodeh_WSGI/server/__init__.py
Faloodeh/Faloodeh_WSGI/server/http_parse.py
Faloodeh/Faloodeh_WSGI/server/http_response.py
Faloodeh/Faloodeh_WSGI/server/server.py
Faloodeh/Faloodeh_WSGI/server/splitbuffer.py
Faloodeh/Faloodeh_WSGI/server/test_http_parse.py
Faloodeh/Faloodeh_WSGI/server/test_splitbuffer.py
Faloodeh/Faloodeh_WSGI/server/wsgi.py
Faloodeh-0.0.2.dist-info/LICENSE
Faloodeh-0.0.2.dist-info/METADATA
Faloodeh-0.0.2.dist-info/WHEEL
Faloodeh-0.0.2.dist-info/top_level.txt
Faloodeh-0.0.2.dist-info/RECORD
